vps_deploy/__init__.py
vps_deploy/django_fabric2.py
vps_deploy-1.2.0.dist-info/COPYING
vps_deploy-1.2.0.dist-info/METADATA
vps_deploy-1.2.0.dist-info/WHEEL
vps_deploy-1.2.0.dist-info/top_level.txt
vps_deploy-1.2.0.dist-info/RECORD
