Metadata-Version: 2.1
Name: vps-deploy
Version: 1.2.0
Summary: Common commands for deployment on a VPS.
Home-page: https://gitlab.com/sturm/vps-deploy
Author: Ben Sturmfels
Author-email: ben@sturm.com.au
Classifier: Development Status :: 5 - Production/Stable
Classifier: Intended Audience :: Developers
Classifier: Topic :: Software Development :: Build Tools
Classifier: License :: OSI Approved :: GNU General Public License v3 or later (GPLv3+)
Classifier: Programming Language :: Python :: 3
Requires-Python: >=3.6
License-File: COPYING
Requires-Dist: fabric >=2.5.0
Requires-Dist: jinja2
Requires-Dist: cryptography >=2.6.1
Requires-Dist: paramiko >=2.4.2
